genro_toolbox/__init__.py
genro_toolbox/ascii_table.py
genro_toolbox/decorators.py
genro_toolbox/dict_utils.py
genro_toolbox/py.typed
genro_toolbox/smartasync.py
genro_toolbox/string_utils.py
genro_toolbox/tags_match.py
genro_toolbox/treedict.py
genro_toolbox/typeutils.py
genro_toolbox/uid.py
genro_toolbox-0.6.2.dist-info/METADATA
genro_toolbox-0.6.2.dist-info/WHEEL
genro_toolbox-0.6.2.dist-info/licenses/LICENSE
genro_toolbox-0.6.2.dist-info/RECORD
