Metadata-Version: 2.4
Name: genro-toolbox
Version: 0.6.2
Summary: Essential utilities for Genro Kyō
Project-URL: Repository, https://github.com/genropy/genro-toolbox
Project-URL: Documentation, https://genro-toolbox.readthedocs.io/en/latest/
Author: Genropy Team
License-Expression: Apache-2.0
License-File: LICENSE
Keywords: decorators,dict-utils,genro,toolbox,utilities
Classifier: Development Status :: 4 - Beta
Classifier: Intended Audience :: Developers
Classifier: License :: OSI Approved :: Apache Software License
Classifier: Operating System :: OS Independent
Classifier: Programming Language :: Python :: 3
Classifier: Programming Language :: Python :: 3 :: Only
Classifier: Topic :: Software Development :: Libraries :: Python Modules
Classifier: Topic :: Utilities
Requires-Python: >=3.10
Provides-Extra: dev
Requires-Dist: ruff>=0.1.0; extra == 'dev'
Provides-Extra: docs
Requires-Dist: myst-parser>=2.0.0; extra == 'docs'
Requires-Dist: sphinx-autodoc-typehints>=2.0.0; extra == 'docs'
Requires-Dist: sphinx-rtd-theme>=3.0.0; extra == 'docs'
Requires-Dist: sphinx>=8.0.0; extra == 'docs'
Requires-Dist: sphinxcontrib-mermaid>=0.9.0; extra == 'docs'
Provides-Extra: test
Requires-Dist: pytest-asyncio>=0.23.0; extra == 'test'
Requires-Dist: pytest-cov>=4.0.0; extra == 'test'
Requires-Dist: pytest>=8.0.0; extra == 'test'
Requires-Dist: pyyaml>=6.0.0; extra == 'test'
